{"name":"Vue","slug":"Vue","count":3,"postlist":[{"title":"Console失效","uid":"85d7f0ee0105da9c47f8cfa58c2659ee","slug":"CannotUseConsole","date":"2022-07-19T08:02:42.000Z","updated":"2022-07-19T08:17:35.303Z","comments":true,"path":"api/articles/CannotUseConsole.json","keywords":null,"cover":null,"text":"console.log()失效问题描述：当使用console.log()想要打印到控制台时，发现idea出现下滑红线，并且num run serve也通不过。 错误信息：ESLint: Unexpected console statement.(no-console) 解决办法：...","link":"","photos":[],"count_time":{"symbolsCount":300,"symbolsTime":"1 mins."},"categories":[{"name":"web前端","slug":"web前端","count":1,"path":"api/categories/web前端.json"}],"tags":[{"name":"Vue","slug":"Vue","count":3,"path":"api/tags/Vue.json"},{"name":"报错","slug":"报错","count":1,"path":"api/tags/报错.json"}],"author":{"name":"LiuQuanZe","slug":"blog-author","avatar":"https://img-blog.csdnimg.cn/20210313122054101.png","link":"/","description":"a good guy!","socials":{"github":"https://github.com/liuquanze","twitter":"","stackoverflow":"","wechat":"","qq":"","weibo":"","zhihu":"","csdn":"https://blog.csdn.net/weixin_45895853","juejin":"","customs":{}}}},{"title":"Vue中localStorage的简单使用","uid":"c4515973a08e01e147ab3e57422101e1","slug":"localStorage","date":"2022-07-21T12:09:11.000Z","updated":"2022-07-21T12:25:59.599Z","comments":true,"path":"api/articles/localStorage.json","keywords":null,"cover":null,"text":"Vue中localStorage的简单使用localStorage主要作为本地存储来使用。下面记录三个主要用法： 存储数据 localStorage.setItem(&#39;key&#39;,&#39;value&#39;) 取出数据 localStorage.getItem(...","link":"","photos":[],"count_time":{"symbolsCount":254,"symbolsTime":"1 mins."},"categories":[{"name":"WEB前端","slug":"WEB前端","count":1,"path":"api/categories/WEB前端.json"}],"tags":[{"name":"Vue","slug":"Vue","count":3,"path":"api/tags/Vue.json"}],"author":{"name":"LiuQuanZe","slug":"blog-author","avatar":"https://img-blog.csdnimg.cn/20210313122054101.png","link":"/","description":"a good guy!","socials":{"github":"https://github.com/liuquanze","twitter":"","stackoverflow":"","wechat":"","qq":"","weibo":"","zhihu":"","csdn":"https://blog.csdn.net/weixin_45895853","juejin":"","customs":{}}}},{"title":"平台开发所使用的前端组件工具","uid":"c37588bd65d4c5745225faacbe87ed1b","slug":"toolsInVue","date":"2022-07-22T13:14:49.000Z","updated":"2022-07-22T13:28:07.361Z","comments":true,"path":"api/articles/toolsInVue.json","keywords":null,"cover":null,"text":"平台开发中所使用到的Vue工具和组件vue-prism-editor1. 实现效果 可输入代码，并且代码语法高亮 支持编辑模式与不可编辑模式 2. 使用步骤 安装依赖 npm install vue-prism-editor 由于vue-prism-editor需要prismjs...","link":"","photos":[],"count_time":{"symbolsCount":"2.1k","symbolsTime":"2 mins."},"categories":[{"name":"Web前端","slug":"Web前端","count":1,"path":"api/categories/Web前端.json"}],"tags":[{"name":"Vue","slug":"Vue","count":3,"path":"api/tags/Vue.json"},{"name":"模块","slug":"模块","count":1,"path":"api/tags/模块.json"}],"author":{"name":"LiuQuanZe","slug":"blog-author","avatar":"https://img-blog.csdnimg.cn/20210313122054101.png","link":"/","description":"a good guy!","socials":{"github":"https://github.com/liuquanze","twitter":"","stackoverflow":"","wechat":"","qq":"","weibo":"","zhihu":"","csdn":"https://blog.csdn.net/weixin_45895853","juejin":"","customs":{}}},"feature":true}]}